jaraco/packaging/__init__.py
jaraco/packaging/make-tree.py
jaraco/packaging/metadata.py
jaraco/packaging/print-metadata.py
jaraco/packaging/sphinx.py
jaraco.packaging-10.2.3.dist-info/LICENSE
jaraco.packaging-10.2.3.dist-info/METADATA
jaraco.packaging-10.2.3.dist-info/WHEEL
jaraco.packaging-10.2.3.dist-info/top_level.txt
jaraco.packaging-10.2.3.dist-info/RECORD
