Metadata-Version: 2.1
Name: jaraco.packaging
Version: 10.2.3
Summary: tools to supplement packaging Python releases
Author-email: "Jason R. Coombs" <jaraco@jaraco.com>
Project-URL: Source, https://github.com/jaraco/jaraco.packaging
Classifier: Development Status :: 5 - Production/Stable
Classifier: Intended Audience :: Developers
Classifier: License :: OSI Approved :: MIT License
Classifier: Programming Language :: Python :: 3
Classifier: Programming Language :: Python :: 3 :: Only
Classifier: Framework :: Sphinx :: Extension
Requires-Python: >=3.8
License-File: LICENSE
Requires-Dist: build[virtualenv]
Requires-Dist: jaraco.context
Requires-Dist: sphinx
Requires-Dist: domdf-python-tools
Provides-Extra: doc
Requires-Dist: sphinx >=3.5 ; extra == 'doc'
Requires-Dist: jaraco.packaging >=9.3 ; extra == 'doc'
Requires-Dist: rst.linker >=1.9 ; extra == 'doc'
Requires-Dist: furo ; extra == 'doc'
Requires-Dist: sphinx-lint ; extra == 'doc'
Provides-Extra: test
Requires-Dist: pytest !=8.1.*,>=6 ; extra == 'test'
Requires-Dist: pytest-checkdocs >=2.4 ; extra == 'test'
Requires-Dist: pytest-cov ; extra == 'test'
Requires-Dist: pytest-mypy ; extra == 'test'
Requires-Dist: pytest-enabler >=2.2 ; extra == 'test'
Requires-Dist: types-docutils ; extra == 'test'
Requires-Dist: pytest-ruff >=0.2.1 ; (sys_platform != "cygwin") and extra == 'test'
